README.rst
setup.cfg
setup.py
itchatmp/__init__.py
itchatmp/config.py
itchatmp/content.py
itchatmp/exceptions.py
itchatmp/log.py
itchatmp/returnvalues.py
itchatmp/server.py
itchatmp/utils.py
itchatmp/components/__init__.py
itchatmp/components/register.py
itchatmp/controllers/__init__.py
itchatmp/controllers/application.py
itchatmp/controllers/chat.py
itchatmp/controllers/common.py
itchatmp/controllers/customerservice.py
itchatmp/controllers/envtest.py
itchatmp/controllers/menu.py
itchatmp/controllers/messages.py
itchatmp/controllers/oauth2.py
itchatmp/controllers/statistics.py
itchatmp/controllers/templatemsgs.py
itchatmp/controllers/users.py
itchatmp/controllers/utils.py
itchatmp/controllers/wrapped.py
itchatmp/controllers/mpapi/__init__.py
itchatmp/controllers/mpapi/base/__init__.py
itchatmp/controllers/mpapi/base/common.py
itchatmp/controllers/mpapi/base/menu.py
itchatmp/controllers/mpapi/mp/__init__.py
itchatmp/controllers/mpapi/mp/common.py
itchatmp/controllers/mpapi/mp/customerservice.py
itchatmp/controllers/mpapi/mp/menu.py
itchatmp/controllers/mpapi/mp/messages.py
itchatmp/controllers/mpapi/mp/statistics.py
itchatmp/controllers/mpapi/mp/templatemsgs.py
itchatmp/controllers/mpapi/mp/users.py
itchatmp/controllers/mpapi/mp/utils.py
itchatmp/controllers/mpapi/mp/wrapped.py
itchatmp/controllers/mpapi/qy/__init__.py
itchatmp/controllers/mpapi/qy/application.py
itchatmp/controllers/mpapi/qy/chat.py
itchatmp/controllers/mpapi/qy/common.py
itchatmp/controllers/mpapi/qy/menu.py
itchatmp/controllers/mpapi/qy/messages.py
itchatmp/controllers/mpapi/qy/oauth2.py
itchatmp/controllers/mpapi/qy/users.py
itchatmp/controllers/mpapi/requests/__init__.py
itchatmp/models/__init__.py
itchatmp/models/common.py
itchatmp/views/__init__.py
itchatmp/views/crypto.py
itchatmp/views/msgconstruct.py
itchatmp/views/templates.py
itchatmp3.egg-info/PKG-INFO
itchatmp3.egg-info/SOURCES.txt
itchatmp3.egg-info/dependency_links.txt
itchatmp3.egg-info/requires.txt
itchatmp3.egg-info/top_level.txt